{
    "phase":5,
    "length":270,
    "name":"P5 Pandora",
    "sections":[
      {
        "id": 0,
        "table":[
          {
            "type":"Raidwide",
            "stakeholder":"all",
            "name":"Targetable",
            "time":0,
            "mitigations":{
              "T1":[
                "Reprisal",
                "Party Mit"
              ],
              "SGE":[
                "Zoe EukProg"
              ],
              "PRange":[
                "Range Mit"
              ]
            }
          },
          {
            "type":"Raidwide",
            "stakeholder":"all",
            "name":"Fulgent Blade 1",
            "time":12,
            "mitigations":{
              "T1":[
                "Reprisal co",
                {
                  "ability": "Party Mit co",
                  "hasOverflow": true
                }
              ],
              "SCH":[
                "Soil"
              ],
              "SGE":[
                "Zoe EukProg co",
                "Kerachole"
              ],
              "AST":[
                "CU"
              ],
              "M2":[
                "Feint"
              ],
              "PRange":[
                "Range Mit co"
              ],
              "MCH":[
                "Dismantle"
              ]
            }
          },
          {
            "type":"Raidwide",
            "stakeholder":"all",
            "name":"Akh Morn 1",
            "time":38,
            "mitigations":{
              "T2":[
                "Reprisal"
              ],
              "SCH":[
                "Recit Spread-Lo",
                "Soil",
                "Expedient"
              ],
              "SGE":[
                "Kerachole",
                "Holos"
              ],
              "M1":[
                "Feint"
              ],
              "Caster":[
                "Addle"
              ],
              "RDM":[
                "Magick Barrier"
              ],
              "extranotes":{
                "SCH":"You can use Expedient on both Polars. The reason it is listed for AM/Polar is to save a wipe from a 3/4 stack for AM"
              }
            }
          },
          {
            "type":"Tankbuster",
            "stakeholder":"all",
            "name":"Wings Dark and Light 1",
            "time":56,
            "mitigations":{
              "WARGNB_WAR":[
                "Holmgang",
                "Nascent Buddy"
              ],
              "WARGNB_GNB":[
                "Kitchen Sink",
                {
                  "ability": "HoC",
                  "note": "Use HoC on 2nd hit"
                }
              ],
              "WARPLD_WAR":[
                "Holmgang",
                "Nascent Buddy"
              ],
              "WARPLD_PLD":[
                "Kitchen Sink"
              ],
              "WARDRK_WAR":[
                "Holmgang",
                "Nascent Buddy"
              ],
              "WARDRK_DRK":[
                "Kitchen Sink",
                {
                  "ability": "TBN",
                  "note": "Use TBN on 2nd hit"
                }
              ],
              "GNBDRK_GNB":[
                "Kitchen Sink"
              ],
              "GNBDRK_DRK":[
                "Living Dead",
                "Oblation Buddy",
                "TBN Buddy"
              ],
              "PLDGNB_PLD":[
                "Hallowed Ground",
                "Intervention"
              ],
              "PLDGNB_GNB":[
                "Kitchen Sink"
              ],
              "PLDDRK_PLD":[
                "Hallowed Ground",
                "Intervention"
              ],
              "PLDDRK_DRK":[
                "Kitchen Sink"
              ],
              "SCH":[
                {
                  "ability": "Seraph",
                  "note": "After last tower"
                }
              ],
              "SGE":[
                {
                  "ability": "Panhaima",
                  "note": "After last tower"
                }
              ],
              "WHM":[
                {
                  "ability": "Temperance",
                  "note": "After last tower"
                }
              ],
              "AST":[
                {
                  "ability": "Neutral",
                  "note": "After last tower"
                }
              ]
            }
          },
          {
            "type":"Raidwide",
            "stakeholder":"all",
            "name":"Polarizing Strikes 1",
            "time":79,
            "mitigations":{
              "T1":[
                "Reprisal"
              ],
              "T2":[
                "Party Mit"
              ],
              "SCH":[
                "Concitation",
                "Soil",
                "Fey Illumination",
                "Expedient"
              ],
              "SGE":[
                "Zoe EukProg",
                "Kerachole"
              ],
              "WHM":[
                "Temperance CO",
                "Bell"
              ],
              "AST":[
                "Neutral co",
                "Sun Sign",
                "CU",
                "Macro"
              ],
              "PRange":[
                {
                  "ability": "Range Mit",
                  "note": "2nd hit of Cruel Path"
                }
              ]
            }
          },
          {
            "type":"Raidwide",
            "stakeholder":"all",
            "name":"Pandora's Box",
            "time":114,
            "mitigations":{
              "T1":[
                "Tank LB"
              ],
              "T2":[
                "Tank LB",
                "Reprisal"
              ],
              "SCH":[
                "Concitation",
                "Soil"
              ],
              "SGE":[
                "EukProg",
                "Kerachole"
              ],
              "extranotes":{
                "SCH":"15s mits on the <b>B</b> in Box, it's more important to catch Fulgent Blade",
                "SGE":"15s mits on the <b>B</b> in Box, it's more important to catch Fulgent Blade"
              }
            }
          },
          {
            "type":"Raidwide",
            "stakeholder":"all",
            "name":"Fulgent Blade 2",
            "time":125,
            "mitigations":{
              "T1":[
                "Party Mit"
              ],
              "T2":[
                "Reprisal co"
              ],
              "SCH":[
                "Concitation",
                "Soil co"
              ],
              "SGE":[
                "EukProg",
                "Kerachole co"
              ],
              "AST":[
                "CU"
              ],
              "M2":[
                "Feint"
              ],
              "PLD":[
                "Wings"
              ]
            }
          },
          {
            "type":"Raidwide",
            "stakeholder":"all",
            "name":"Akh Morn 2",
            "time":150,
            "mitigations":{
              "T1":[
                "Reprisal"
              ],
              "SCH":[
                "Recit Spread-Lo",
                "Soil"
              ],
              "SGE":[
                "EukProg",
                "Kerachole"
              ],
              "AST":[
                "CU"
              ],
              "M1":[
                "Feint"
              ],
              "Caster":[
                "Addle"
              ]
            }
          },
          {
            "type":"Tankbuster",
            "stakeholder":"tanks",
            "name":"Wings Dark and Light 2",
            "time":176,
            "mitigations":{
              "WARGNB_WAR":[
                "Kitchen Sink"
              ],
              "WARGNB_GNB":[
                "Superbolide",
                "HoC Buddy"
              ],
              "WARPLD_WAR":[
                "Kitchen Sink"
              ],
              "WARPLD_PLD":[
                "Hallowed Ground",
                "Intervention"
              ],
              "WARDRK_WAR":[
                "Kitchen Sink"
              ],
              "WARDRK_DRK":[
                "Living Dead",
                "Oblation Buddy",
                "TBN Buddy"
              ],
              "GNBDRK_GNB":[
                "Superbolide",
                "HoC buddy"
              ],
              "GNBDRK_DRK":[
                "Kitchen Sink"
              ],
              "PLDGNB_PLD":[
                "Kitchen Sink"
              ],
              "PLDGNB_GNB":[
                "Superbolide",
                "HoC Buddy"
              ],
              "PLDDRK_PLD":[
                "Kitchen Sink"
              ],
              "PLDDRK_DRK":[
                "Living Dead",
                "TBN Buddy",
                "Oblation Buddy"
              ],
              "SCH":[
                {
                  "ability": "Soil",
                  "note": "After last tower"
                }
              ],
              "SGE":[
                {
                  "ability": "Kerachole",
                  "note": "After last tower"
                }
              ]
            }
          },
          {
            "type":"Raidwide",
            "stakeholder":"all",
            "name":"Polarizing Strikes 2",
            "time":191,
            "mitigations":{
              "T2":[
                "Reprisal",
                "Party Mit"
              ],
              "SCH":[
                "Seraph",
                "Expedient",
                "Soil",
                "Seraphism",
                "Fey Illumination"
              ],
              "SGE":[
                "Zoe EukProg",
                "Panhaima",
                "Philosophia"
              ],
              "WHM":[
                "Temperance"
              ],
              "AST":[
                "Neutral",
                "Sun Sign",
                "Macro"
              ],
              "PRange":[
                "Range Mit"
              ],
              "RDM":[
                {
                  "ability": "Barrier",
                  "note": "2nd hit of Cruel Path"
                }
              ]
            }
          },
          {
            "type":"Raidwide",
            "stakeholder":"all",
            "name":"Fulgent Blade 3",
            "time":215,
            "mitigations":{
              "T1":[
                "Reprisal",
                "Party Mit"
              ],
              "SCH":[
                "Soil"
              ],
              "SGE":[
                "EukProg",
                "Kerachole"
              ],
              "M2":[
                "Feint"
              ],
              "MCH":[
                "Dismantle"
              ]
            }
          },
          {
            "type":"Raidwide",
            "stakeholder":"all",
            "name":"Akh Morn 3",
            "time":242,
            "mitigations":{
              "T2":[
                "Reprisal"
              ],
              "SCH":[
                "Recit Spread-Lo",
                "Soil"
              ],
              "SGE":[
                "Holos",
                "Kerachole"
              ],
              "AST":[
                "CU"
              ],
              "M1":[
                "Feint"
              ],
              "Caster":[
                "Addle"
              ],
              "PLD":[
                "Wings"
              ]
            }
          }
        ]
      }
    ]
  }